odoo/addons/rma_sale_reason/README.rst
odoo/addons/rma_sale_reason/__init__.py
odoo/addons/rma_sale_reason/__manifest__.py
odoo/addons/rma_sale_reason/controllers/__init__.py
odoo/addons/rma_sale_reason/controllers/rma_portal.py
odoo/addons/rma_sale_reason/i18n/it.po
odoo/addons/rma_sale_reason/i18n/rma_sale_reason.pot
odoo/addons/rma_sale_reason/readme/CONTRIBUTORS.md
odoo/addons/rma_sale_reason/readme/DESCRIPTION.md
odoo/addons/rma_sale_reason/readme/USAGE.md
odoo/addons/rma_sale_reason/static/description/icon.png
odoo/addons/rma_sale_reason/static/description/index.html
odoo/addons/rma_sale_reason/static/src/js/rma_portal_form.esm.js
odoo/addons/rma_sale_reason/static/src/tests/test_rma_sale_portal_tour.esm.js
odoo/addons/rma_sale_reason/tests/__init__.py
odoo/addons/rma_sale_reason/tests/test_rma_sale_portal.py
odoo/addons/rma_sale_reason/tests/test_rma_sale_reason.py
odoo/addons/rma_sale_reason/views/rma_portal_templates.xml
odoo/addons/rma_sale_reason/wizards/__init__.py
odoo/addons/rma_sale_reason/wizards/sale_order_line_rma_wizard.py
odoo/addons/rma_sale_reason/wizards/sale_order_rma_wizard.py
odoo/addons/rma_sale_reason/wizards/sale_order_rma_wizard.xml
odoo_addon_rma_sale_reason-18.0.1.0.0.2.dist-info/METADATA
odoo_addon_rma_sale_reason-18.0.1.0.0.2.dist-info/WHEEL
odoo_addon_rma_sale_reason-18.0.1.0.0.2.dist-info/top_level.txt
odoo_addon_rma_sale_reason-18.0.1.0.0.2.dist-info/RECORD
